CHANGES.rst
MANIFEST.in
README.rst
TODO.txt
requirements.txt
setup.py
docs/INSTALL.txt
docs/LICENSE.GPL
docs/LICENSE.txt
src/plone/__init__.py
src/plone.app.workflowmanager.egg-info/PKG-INFO
src/plone.app.workflowmanager.egg-info/SOURCES.txt
src/plone.app.workflowmanager.egg-info/dependency_links.txt
src/plone.app.workflowmanager.egg-info/entry_points.txt
src/plone.app.workflowmanager.egg-info/namespace_packages.txt
src/plone.app.workflowmanager.egg-info/not-zip-safe
src/plone.app.workflowmanager.egg-info/requires.txt
src/plone.app.workflowmanager.egg-info/top_level.txt
src/plone/app/__init__.py
src/plone/app/workflowmanager/__init__.py
src/plone/app/workflowmanager/actionmanager.py
src/plone/app/workflowmanager/browser.txt
src/plone/app/workflowmanager/configure.zcml
src/plone/app/workflowmanager/graphviz.py
src/plone/app/workflowmanager/permissions.py
src/plone/app/workflowmanager/testing.py
src/plone/app/workflowmanager/utils.py
src/plone/app/workflowmanager/browser/__init__.py
src/plone/app/workflowmanager/browser/actions.py
src/plone/app/workflowmanager/browser/configure.zcml
src/plone/app/workflowmanager/browser/controlpanel.py
src/plone/app/workflowmanager/browser/layout.py
src/plone/app/workflowmanager/browser/state.py
src/plone/app/workflowmanager/browser/transition.py
src/plone/app/workflowmanager/browser/validators.py
src/plone/app/workflowmanager/browser/workflow.py
src/plone/app/workflowmanager/browser/resources/bootstrap-orig.css
src/plone/app/workflowmanager/browser/resources/bootstrap-popover.js
src/plone/app/workflowmanager/browser/resources/bootstrap.css
src/plone/app/workflowmanager/browser/resources/fix-bootstrap.py
src/plone/app/workflowmanager/browser/resources/js_tests.js
src/plone/app/workflowmanager/browser/resources/springy.js
src/plone/app/workflowmanager/browser/resources/springyui.js
src/plone/app/workflowmanager/browser/resources/workflow-graph.css
src/plone/app/workflowmanager/browser/resources/workflow-graph.js
src/plone/app/workflowmanager/browser/resources/workflowmanager.css
src/plone/app/workflowmanager/browser/resources/workflowmanager.js
src/plone/app/workflowmanager/browser/resources/jsPlumb/dom.jsPlumb-1.6.2-min.js
src/plone/app/workflowmanager/browser/templates/add-action.pt
src/plone/app/workflowmanager/browser/templates/add-new-state.pt
src/plone/app/workflowmanager/browser/templates/add-new-transition.pt
